openpecha/__init__.py
openpecha/config.py
openpecha/exceptions.py
openpecha/ids.py
openpecha/utils.py
openpecha/alignment/__init__.py
openpecha/buda/__init__.py
openpecha/buda/api.py
openpecha/pecha/__init__.py
openpecha/pecha/annotations.py
openpecha/pecha/blupdate.py
openpecha/pecha/layer.py
openpecha/pecha/metadata.py
openpecha/pecha/parsers/__init__.py
openpecha/pecha/parsers/edition.py
openpecha/pecha/serializers/__init__.py
openpecha/pecha/serializers/json.py
openpecha-2.4.5.dist-info/licenses/LICENSE
openpecha-2.4.5.dist-info/METADATA
openpecha-2.4.5.dist-info/WHEEL
openpecha-2.4.5.dist-info/top_level.txt
openpecha-2.4.5.dist-info/RECORD
