Metadata-Version: 2.4
Name: openpecha
Version: 2.4.5
Summary: OpenPecha toolkit version 2
Author-email: Tashi Tsering <tashitsering@esukhia.org>, Tenzin Tsundue <tsundue@esukhia.org>
Project-URL: Homepage, https://github.com/OpenPecha/openpecha-project-template
Project-URL: Bug Tracker, https://github.com/OpenPecha/openpecha-project-template/issues
Classifier: Programming Language :: Python :: 3
Classifier: License :: OSI Approved :: MIT License
Classifier: Operating System :: OS Independent
Requires-Python: >=3.10
License-File: LICENSE
Requires-Dist: pydantic>=2.7.4
Requires-Dist: stam==0.9.0
Requires-Dist: diff-match-patch==20230430
Requires-Dist: pyewts==0.2.0
Requires-Dist: botok>=0.8.12
Requires-Dist: python-docx>=1.1.2
Requires-Dist: fast_antx==0.0.1
Requires-Dist: bo_sent_tokenizer==0.0.1
Requires-Dist: docx2python==3.3.0
Requires-Dist: boto3>=1.34.0
Requires-Dist: botocore>=1.34.0
Requires-Dist: rdflib>=5.0.0
Requires-Dist: fonttools[unicode]>=4.37.3
Requires-Dist: beautifulsoup4>=4.12.0
Provides-Extra: dev
Requires-Dist: pytest; extra == "dev"
Requires-Dist: pytest-cov; extra == "dev"
Requires-Dist: pre-commit; extra == "dev"
Provides-Extra: docs
Requires-Dist: sphinx>=7.0.0; extra == "docs"
Requires-Dist: sphinx-rtd-theme>=1.3.0; extra == "docs"
Requires-Dist: myst-parser>=2.0.0; extra == "docs"
Requires-Dist: sphinx-autodoc-typehints>=1.25.0; extra == "docs"
Dynamic: license-file
